COPYING
MANIFEST.in
setup.py
Wicken.egg-info/PKG-INFO
Wicken.egg-info/SOURCES.txt
Wicken.egg-info/dependency_links.txt
Wicken.egg-info/requires.txt
Wicken.egg-info/top_level.txt
wicken/__init__.py
wicken/dictionary_dogma.py
wicken/dogma.py
wicken/exceptions.py
wicken/netcdf_dogma.py
wicken/util.py
wicken/xml_dogma.py