Metadata-Version: 1.1
Name: Wicken
Version: 0.1.2
Summary: Maps metadata concepts to concrete specifations and file formats
Home-page: https://github.com/ioos/wicken
Author: David Stuebe
Author-email: DStuebe@ASAScience.com
License: GPLv3
Keywords: Metadata ISO OGC NetCDF lxml xml ncml
Platform: UNKNOWN
Classifier: Development Status :: 3 - Alpha
Classifier: Intended Audience :: Developers
Classifier: Intended Audience :: Science/Research
Classifier: License :: OSI Approved :: GNU General Public License v3 (GPLv3)
Classifier: Operating System :: POSIX :: Linux
Classifier: Programming Language :: Python
Classifier: Topic :: Scientific/Engineering
